{"name":"Comprar producto exito","id":"comprar-producto-exito;comprar-producto-exito","testSteps":[{"number":1,"description":"Given El usuario esta en la pagina del exito con su cuenta registrada","duration":18029,"startTime":"2023-04-01T17:56:34.958598200-04:00[America/Caracas]","screenshots":[{"screenshot":"b91072ab3d9ca425bee12da27055626c3131ffc97dc86512d1cdd3fdc23fef4e.png","timeStamp":1680386212987}],"result":"SUCCESS","precondition":false,"level":0,"children":[{"number":2,"description":"Santy abrir pagina inicial","duration":7925,"startTime":"2023-04-01T17:56:39.572683100-04:00[America/Caracas]","screenshots":[{"screenshot":"eafeaa3fb7da7e39c2f6290aacb5c03acde6480fb90e8e470f11dc51538fb87f.png","timeStamp":1680386200155},{"screenshot":"40f9639d958b839573d41947606fdaffd0c308e6dbdc45a642f9d6198c82aa8f.png","timeStamp":1680386207498}],"result":"SUCCESS","precondition":false,"level":1,"children":[{"number":3,"description":"Santy opens the Pagina inicial","duration":7296,"startTime":"2023-04-01T17:56:40.178504800-04:00[America/Caracas]","screenshots":[{"screenshot":"eafeaa3fb7da7e39c2f6290aacb5c03acde6480fb90e8e470f11dc51538fb87f.png","timeStamp":1680386200196},{"screenshot":"40f9639d958b839573d41947606fdaffd0c308e6dbdc45a642f9d6198c82aa8f.png","timeStamp":1680386207474}],"result":"SUCCESS","precondition":false,"level":2}]},{"number":4,"description":"Santy iniciar sesion","duration":5090,"startTime":"2023-04-01T17:56:47.515098500-04:00[America/Caracas]","screenshots":[{"screenshot":"e4415c0a0d6ced35bebdf2c04c61ad658791a2b26abba94aaace5261537da1b4.png","timeStamp":1680386207997},{"screenshot":"6432352573d3e6bc8c16d024d726449660002b452edb69fb1a2e93fa92564870.png","timeStamp":1680386212605}],"result":"SUCCESS","precondition":false,"level":1,"children":[{"number":5,"description":"Santy clicks on Boton para iniciar sesion","duration":1112,"startTime":"2023-04-01T17:56:48.030784200-04:00[America/Caracas]","screenshots":[{"screenshot":"da3f8d891a42d17e94c45812b74f63ef725782fdb630fbe2c8da8f6ebd2dacf1.png","timeStamp":1680386208466},{"screenshot":"5f1e039b3d5821947ffda6448ddf855260c2a5101bcd770711e83f1e07b5e7aa.png","timeStamp":1680386209143}],"result":"SUCCESS","precondition":false,"level":2},{"number":6,"description":"Santy clicks on campo usuario","duration":564,"startTime":"2023-04-01T17:56:49.144495100-04:00[America/Caracas]","screenshots":[{"screenshot":"5f1e039b3d5821947ffda6448ddf855260c2a5101bcd770711e83f1e07b5e7aa.png","timeStamp":1680386209157},{"screenshot":"7d3588bc2abe23295a947968b4988a214efc6205ae7a2483b59f237938d61682.png","timeStamp":1680386209708}],"result":"SUCCESS","precondition":false,"level":2},{"number":7,"description":"Santy clicks on Campo email iniciar sesion","duration":550,"startTime":"2023-04-01T17:56:49.710122400-04:00[America/Caracas]","screenshots":[{"screenshot":"7d3588bc2abe23295a947968b4988a214efc6205ae7a2483b59f237938d61682.png","timeStamp":1680386209722},{"screenshot":"38271c58f84db950bb83ea1719c880288986dafed8a93088201bc4221d6687b7.png","timeStamp":1680386210259}],"result":"SUCCESS","precondition":false,"level":2},{"number":8,"description":"Santy enters \u0027santiokami.23@gmail.com\u0027 into Campo email iniciar sesion","duration":1010,"startTime":"2023-04-01T17:56:50.262171600-04:00[America/Caracas]","screenshots":[{"screenshot":"38271c58f84db950bb83ea1719c880288986dafed8a93088201bc4221d6687b7.png","timeStamp":1680386210272},{"screenshot":"a5a8c1a2f3e6c9137b08a89d92a8b20c4f921fb383c2758490f87092da801e12.png","timeStamp":1680386211272}],"result":"SUCCESS","precondition":false,"level":2},{"number":9,"description":"Santy enters \u0027Santy123456\u0027 into Campo contrasenna iniciar sesion","duration":791,"startTime":"2023-04-01T17:56:51.276038900-04:00[America/Caracas]","screenshots":[{"screenshot":"a5a8c1a2f3e6c9137b08a89d92a8b20c4f921fb383c2758490f87092da801e12.png","timeStamp":1680386211285},{"screenshot":"4ed7e1d1541cbc9273d4dfcbcec99e34d5ab07836b6bcec41c965ea83a9ec5a7.png","timeStamp":1680386212067}],"result":"SUCCESS","precondition":false,"level":2},{"number":10,"description":"Santy clicks on Boton ingresar cuenta","duration":518,"startTime":"2023-04-01T17:56:52.068627-04:00[America/Caracas]","screenshots":[{"screenshot":"4ed7e1d1541cbc9273d4dfcbcec99e34d5ab07836b6bcec41c965ea83a9ec5a7.png","timeStamp":1680386212080},{"screenshot":"6432352573d3e6bc8c16d024d726449660002b452edb69fb1a2e93fa92564870.png","timeStamp":1680386212586}],"result":"SUCCESS","precondition":false,"level":2}]}]},{"number":11,"description":"When Selecciona un producto de una categoria","duration":82409,"startTime":"2023-04-01T17:56:52.991827700-04:00[America/Caracas]","screenshots":[{"screenshot":"9c890713b96198a6f4f3688a8a6d7b994eb0b07f7a7a98821305767630d2a8c0.png","timeStamp":1680386295401}],"result":"SUCCESS","precondition":false,"level":0,"children":[{"number":12,"description":"Santy seleccionar tipo de envio","duration":18641,"startTime":"2023-04-01T17:56:58.048404400-04:00[America/Caracas]","screenshots":[{"screenshot":"b56d679989eb84bff07cd44649882e0d7406320cdcf2023d89b774062da698ef.png","timeStamp":1680386229675},{"screenshot":"36a45350b6051feca3372c332867cd62405de51b91b9b991b6c959f83440cae3.png","timeStamp":1680386236689}],"result":"SUCCESS","precondition":false,"level":1,"children":[{"number":13,"description":"Santy clicks on Seleccionar tipo de envio","duration":1162,"startTime":"2023-04-01T17:57:09.716982600-04:00[America/Caracas]","screenshots":[{"screenshot":"55f43ad436ee1006f5486e25b3964cd3ab76ebb36da70b67840f9d2dc511849f.png","timeStamp":1680386230335},{"screenshot":"402e530f5c78f3a8be0825bbee4648e2934dad0a41501ca6d54d6b66b5468d38.png","timeStamp":1680386230879}],"result":"SUCCESS","precondition":false,"level":2},{"number":14,"description":"Santy clicks on Seleccionar ciudad","duration":1510,"startTime":"2023-04-01T17:57:10.881793-04:00[America/Caracas]","screenshots":[{"screenshot":"402e530f5c78f3a8be0825bbee4648e2934dad0a41501ca6d54d6b66b5468d38.png","timeStamp":1680386230896},{"screenshot":"a571c074e1c10c2b4f1c4dfcf3ed28597206403f48120942d1ded138904559aa.png","timeStamp":1680386232392}],"result":"SUCCESS","precondition":false,"level":2},{"number":15,"description":"Santy enters \u0027Cali\u0027 into Seleccionar ciudad","duration":803,"startTime":"2023-04-01T17:57:12.394253800-04:00[America/Caracas]","screenshots":[{"screenshot":"a571c074e1c10c2b4f1c4dfcf3ed28597206403f48120942d1ded138904559aa.png","timeStamp":1680386232402},{"screenshot":"8343c2f01489ae44d8ec0a9402905078129f3b722df05dada0d03c738ea9b8dd.png","timeStamp":1680386233197}],"result":"SUCCESS","precondition":false,"level":2},{"number":16,"description":"Santy types \u0027ENTER\u0027 in Seleccionar ciudad","duration":461,"startTime":"2023-04-01T17:57:13.199509700-04:00[America/Caracas]","screenshots":[{"screenshot":"8343c2f01489ae44d8ec0a9402905078129f3b722df05dada0d03c738ea9b8dd.png","timeStamp":1680386233212},{"screenshot":"842046f0cb7387d359783c998399f5dc62cd2c5785a5442a9652334374f2606f.png","timeStamp":1680386233660}],"result":"SUCCESS","precondition":false,"level":2},{"number":17,"description":"Santy clicks on Seleccionar tienda","duration":572,"startTime":"2023-04-01T17:57:13.663010900-04:00[America/Caracas]","screenshots":[{"screenshot":"842046f0cb7387d359783c998399f5dc62cd2c5785a5442a9652334374f2606f.png","timeStamp":1680386233678},{"screenshot":"9d2e81c9b04cc1cf64199d57c6af0ab268a7e8029348278c03ddf49a2fb116da.png","timeStamp":1680386234235}],"result":"SUCCESS","precondition":false,"level":2},{"number":18,"description":"Santy enters \u0027Exito La Flora\u0027 into Seleccionar tienda","duration":866,"startTime":"2023-04-01T17:57:14.238119400-04:00[America/Caracas]","screenshots":[{"screenshot":"9d2e81c9b04cc1cf64199d57c6af0ab268a7e8029348278c03ddf49a2fb116da.png","timeStamp":1680386234251},{"screenshot":"f0d4fda9af8113665c8a3936312c3fd5f3037f4d9056c2796841b402b8eae9f2.png","timeStamp":1680386235104}],"result":"SUCCESS","precondition":false,"level":2},{"number":19,"description":"Santy types \u0027ENTER\u0027 in Seleccionar tienda","duration":403,"startTime":"2023-04-01T17:57:15.106365800-04:00[America/Caracas]","screenshots":[{"screenshot":"f0d4fda9af8113665c8a3936312c3fd5f3037f4d9056c2796841b402b8eae9f2.png","timeStamp":1680386235117},{"screenshot":"2f544d21b420bb1ff39db6ecf4700734b5648cc4ddd7d6c7405422cc85a2c27e.png","timeStamp":1680386235509}],"result":"SUCCESS","precondition":false,"level":2},{"number":20,"description":"Santy clicks on Boton seleccionar tipo de envio","duration":542,"startTime":"2023-04-01T17:57:15.511446100-04:00[America/Caracas]","screenshots":[{"screenshot":"2f544d21b420bb1ff39db6ecf4700734b5648cc4ddd7d6c7405422cc85a2c27e.png","timeStamp":1680386235521},{"screenshot":"59d8c60ebe4ffadce0f7409e3f807e3d994a4710177a2a374c2133b13e5562e6.png","timeStamp":1680386236053}],"result":"SUCCESS","precondition":false,"level":2},{"number":21,"description":"Santy clicks on Cerrar PopUp Selección de tipo de envio","duration":624,"startTime":"2023-04-01T17:57:16.054844200-04:00[America/Caracas]","screenshots":[{"screenshot":"59d8c60ebe4ffadce0f7409e3f807e3d994a4710177a2a374c2133b13e5562e6.png","timeStamp":1680386236065},{"screenshot":"36a45350b6051feca3372c332867cd62405de51b91b9b991b6c959f83440cae3.png","timeStamp":1680386236679}],"result":"SUCCESS","precondition":false,"level":2}]},{"number":22,"description":"Santy seleccion mercado","duration":4035,"startTime":"2023-04-01T17:57:21.709654500-04:00[America/Caracas]","screenshots":[{"screenshot":"bc62865b18b8a1d46ace8c38a5167e36caf4c481569ca8f68034658258dd27ea.png","timeStamp":1680386242089},{"screenshot":"2a1604a57c4c6c3902e68e2ddf84588879f138c7774349ac8f08df54a487f7fc.png","timeStamp":1680386245744}],"result":"SUCCESS","precondition":false,"level":1,"children":[{"number":23,"description":"Santy clicks on Campo para ingresar el tipo de producto","duration":687,"startTime":"2023-04-01T17:57:22.099051100-04:00[America/Caracas]","screenshots":[{"screenshot":"bc62865b18b8a1d46ace8c38a5167e36caf4c481569ca8f68034658258dd27ea.png","timeStamp":1680386242112},{"screenshot":"1e6b247bff61f7032de262783b6d54f40eef3b39e88f6af9c5cc3d0847d24abb.png","timeStamp":1680386242786}],"result":"SUCCESS","precondition":false,"level":2},{"number":24,"description":"Santy enters \u0027Mortadela\u0027 into Campo para ingresar el tipo de producto","duration":900,"startTime":"2023-04-01T17:57:22.789137700-04:00[America/Caracas]","screenshots":[{"screenshot":"1e6b247bff61f7032de262783b6d54f40eef3b39e88f6af9c5cc3d0847d24abb.png","timeStamp":1680386242807},{"screenshot":"162ae445b8f63e48380328470a2db4d0e26f9195b1be0f3b3ef684a189f1e39c.png","timeStamp":1680386243689}],"result":"SUCCESS","precondition":false,"level":2},{"number":25,"description":"Santy clicks on Cliqueable de la lupa para buscar producto","duration":896,"startTime":"2023-04-01T17:57:23.690455900-04:00[America/Caracas]","screenshots":[{"screenshot":"162ae445b8f63e48380328470a2db4d0e26f9195b1be0f3b3ef684a189f1e39c.png","timeStamp":1680386243700},{"screenshot":"928a25dbe7cc73154ecf75c7e265bc1e3b1d17a0da91af7352b24cb667b54d97.png","timeStamp":1680386244586}],"result":"SUCCESS","precondition":false,"level":2},{"number":26,"description":"Santy types \u0027ENTER\u0027 in Campo para ingresar el tipo de producto","duration":1139,"startTime":"2023-04-01T17:57:24.590402300-04:00[America/Caracas]","screenshots":[{"screenshot":"928a25dbe7cc73154ecf75c7e265bc1e3b1d17a0da91af7352b24cb667b54d97.png","timeStamp":1680386244618},{"screenshot":"2a1604a57c4c6c3902e68e2ddf84588879f138c7774349ac8f08df54a487f7fc.png","timeStamp":1680386245729}],"result":"SUCCESS","precondition":false,"level":2}]},{"number":27,"description":"Santy filtrar producto menor precio","duration":1407,"startTime":"2023-04-01T17:57:30.760716300-04:00[America/Caracas]","screenshots":[{"screenshot":"8e72bc194b02bdd7a06029f3118bc3d49bec423209b9e544f5d287659c207f9f.png","timeStamp":1680386250969},{"screenshot":"6240c5df51e18ca44e42ef3ce995380c77d77e25aa0a307818d4e9d6a444dbaa.png","timeStamp":1680386252168}],"result":"SUCCESS","precondition":false,"level":1,"children":[{"number":28,"description":"Santy clicks on Click en filtrar producto","duration":416,"startTime":"2023-04-01T17:57:30.975477900-04:00[America/Caracas]","screenshots":[{"screenshot":"8e72bc194b02bdd7a06029f3118bc3d49bec423209b9e544f5d287659c207f9f.png","timeStamp":1680386250984},{"screenshot":"03db404331c47d92baa55c2d2e08c579b632abf2729f9204e5b3d10dd439ed35.png","timeStamp":1680386251392}],"result":"SUCCESS","precondition":false,"level":2},{"number":29,"description":"Santy clicks on Click en menor costo","duration":757,"startTime":"2023-04-01T17:57:31.393475900-04:00[America/Caracas]","screenshots":[{"screenshot":"03db404331c47d92baa55c2d2e08c579b632abf2729f9204e5b3d10dd439ed35.png","timeStamp":1680386251408},{"screenshot":"6240c5df51e18ca44e42ef3ce995380c77d77e25aa0a307818d4e9d6a444dbaa.png","timeStamp":1680386252151}],"result":"SUCCESS","precondition":false,"level":2}]},{"number":30,"description":"Santy agregar producto carrito","duration":1555,"startTime":"2023-04-01T17:57:37.191390300-04:00[America/Caracas]","screenshots":[{"screenshot":"5e4f7fa7ced2b0386e5805e7fd54ca53553423a29672322dac25319c8362b99b.png","timeStamp":1680386257416},{"screenshot":"43d86c33ae52bc40b2ec5b9649275b7e52962388282c381ae987eea734c26b3c.png","timeStamp":1680386258746}],"result":"SUCCESS","precondition":false,"level":1,"children":[{"number":31,"description":"Santy clicks on Seleccionar tipo de envio","duration":1052,"startTime":"2023-04-01T17:57:37.680088700-04:00[America/Caracas]","screenshots":[{"screenshot":"5e4f7fa7ced2b0386e5805e7fd54ca53553423a29672322dac25319c8362b99b.png","timeStamp":1680386257892},{"screenshot":"43d86c33ae52bc40b2ec5b9649275b7e52962388282c381ae987eea734c26b3c.png","timeStamp":1680386258732}],"result":"SUCCESS","precondition":false,"level":2}]},{"number":32,"description":"Santy digirse al carrito","duration":7752,"startTime":"2023-04-01T17:57:43.760967900-04:00[America/Caracas]","screenshots":[{"screenshot":"9b39d99f2eacebaa678ef5a654faf975fc4ebf1d6b413bfe106e5913683bca40.png","timeStamp":1680386264055},{"screenshot":"47df20e08ebf56060bd07323b0295e016e970ea7b901fa83ed9b43181e536bc5.png","timeStamp":1680386271513}],"result":"SUCCESS","precondition":false,"level":1,"children":[{"number":33,"description":"Santy clicks on Entrar al carrito de compras","duration":7195,"startTime":"2023-04-01T17:57:44.293652600-04:00[America/Caracas]","screenshots":[{"screenshot":"444a500f556ddbfd664e0b4940c5fc9a08ba1f9cebcd42b3cf47bf984b862e62.png","timeStamp":1680386264636},{"screenshot":"47df20e08ebf56060bd07323b0295e016e970ea7b901fa83ed9b43181e536bc5.png","timeStamp":1680386271489}],"result":"SUCCESS","precondition":false,"level":2}]},{"number":34,"description":"Santy ir a pagar","duration":1160,"startTime":"2023-04-01T17:57:56.537954600-04:00[America/Caracas]","screenshots":[{"screenshot":"47df20e08ebf56060bd07323b0295e016e970ea7b901fa83ed9b43181e536bc5.png","timeStamp":1680386276704},{"screenshot":"fbc44aef2f3d7c39ad5a720bf80e42839f388bd09b8cba59d30d3804bcd5c838.png","timeStamp":1680386277698}],"result":"SUCCESS","precondition":false,"level":1,"children":[{"number":35,"description":"Santy clicks on Ir a pagar lo que hay en el carrito de compra","duration":734,"startTime":"2023-04-01T17:57:56.950072400-04:00[America/Caracas]","screenshots":[{"screenshot":"47df20e08ebf56060bd07323b0295e016e970ea7b901fa83ed9b43181e536bc5.png","timeStamp":1680386277143},{"screenshot":"fbc44aef2f3d7c39ad5a720bf80e42839f388bd09b8cba59d30d3804bcd5c838.png","timeStamp":1680386277684}],"result":"SUCCESS","precondition":false,"level":2}]},{"number":36,"description":"Santy refreshes the browser","duration":3184,"startTime":"2023-04-01T17:57:57.708392500-04:00[America/Caracas]","screenshots":[{"screenshot":"fbc44aef2f3d7c39ad5a720bf80e42839f388bd09b8cba59d30d3804bcd5c838.png","timeStamp":1680386277731},{"screenshot":"fbc44aef2f3d7c39ad5a720bf80e42839f388bd09b8cba59d30d3804bcd5c838.png","timeStamp":1680386280892}],"result":"SUCCESS","precondition":false,"level":1},{"number":37,"description":"Santy llenar datos comprador finalizar compra","duration":8322,"startTime":"2023-04-01T17:58:00.903050400-04:00[America/Caracas]","screenshots":[{"screenshot":"fbc44aef2f3d7c39ad5a720bf80e42839f388bd09b8cba59d30d3804bcd5c838.png","timeStamp":1680386280914},{"screenshot":"2e5862f3aeea96a9822455880bbcb341d63aac71963cdeb2eb1f45a9e0846ecc.png","timeStamp":1680386289225}],"result":"SUCCESS","precondition":false,"level":1,"children":[{"number":38,"description":"Santy clears field Campo nombre para finalizar la compra","duration":605,"startTime":"2023-04-01T17:58:00.953767300-04:00[America/Caracas]","screenshots":[{"screenshot":"fbc44aef2f3d7c39ad5a720bf80e42839f388bd09b8cba59d30d3804bcd5c838.png","timeStamp":1680386281120},{"screenshot":"78511c93799f557d5d0127dd9a159631782930ed25f2ef6a8ca5543287495e39.png","timeStamp":1680386281558}],"result":"SUCCESS","precondition":false,"level":2},{"number":39,"description":"Santy enters \u0027Juan\u0027 into Campo nombre para finalizar la compra","duration":613,"startTime":"2023-04-01T17:58:01.560839100-04:00[America/Caracas]","screenshots":[{"screenshot":"78511c93799f557d5d0127dd9a159631782930ed25f2ef6a8ca5543287495e39.png","timeStamp":1680386281574},{"screenshot":"b01922cef9e93cd51f07890d38e3311adbd8617830ab2fd59b2175f0bdae8812.png","timeStamp":1680386282174}],"result":"SUCCESS","precondition":false,"level":2},{"number":40,"description":"Santy clears field Campo apellido para finalizar la compra","duration":600,"startTime":"2023-04-01T17:58:02.176221-04:00[America/Caracas]","screenshots":[{"screenshot":"b01922cef9e93cd51f07890d38e3311adbd8617830ab2fd59b2175f0bdae8812.png","timeStamp":1680386282186},{"screenshot":"f22447ede7c88cab73682825a8f061b820605883a7b100834873c1394aa950a6.png","timeStamp":1680386282776}],"result":"SUCCESS","precondition":false,"level":2},{"number":41,"description":"Santy enters \u0027Perez\u0027 into Campo apellido para finalizar la compra","duration":812,"startTime":"2023-04-01T17:58:02.777560300-04:00[America/Caracas]","screenshots":[{"screenshot":"f22447ede7c88cab73682825a8f061b820605883a7b100834873c1394aa950a6.png","timeStamp":1680386282789},{"screenshot":"001876a70326eff92c4ce8e0877264134428df3458edeb508b250aba36b826ee.png","timeStamp":1680386283590}],"result":"SUCCESS","precondition":false,"level":2},{"number":42,"description":"Santy clears field Campo celular para finalizar la compra","duration":405,"startTime":"2023-04-01T17:58:03.591125400-04:00[America/Caracas]","screenshots":[{"screenshot":"001876a70326eff92c4ce8e0877264134428df3458edeb508b250aba36b826ee.png","timeStamp":1680386283602},{"screenshot":"f4ef4acdc7a31e6bcacb1ef65d16be3b32e565074ebad08be77ebb21fd0f2cee.png","timeStamp":1680386283996}],"result":"SUCCESS","precondition":false,"level":2},{"number":43,"description":"Santy enters \u00273148271191\u0027 into Campo celular para finalizar la compra","duration":641,"startTime":"2023-04-01T17:58:03.998945500-04:00[America/Caracas]","screenshots":[{"screenshot":"f4ef4acdc7a31e6bcacb1ef65d16be3b32e565074ebad08be77ebb21fd0f2cee.png","timeStamp":1680386284015},{"screenshot":"03f174bb46fdfacd648d9d156f16b1dc761f88e4f58ac08cef90fdd2334e9166.png","timeStamp":1680386284640}],"result":"SUCCESS","precondition":false,"level":2},{"number":44,"description":"Santy clears field Campo numero de cedula para finalizar la compra","duration":450,"startTime":"2023-04-01T17:58:04.643245100-04:00[America/Caracas]","screenshots":[{"screenshot":"03f174bb46fdfacd648d9d156f16b1dc761f88e4f58ac08cef90fdd2334e9166.png","timeStamp":1680386284674},{"screenshot":"22ce698dd032345500a96ad510b64aaae226513ed73bc10330cd63e593db6bf4.png","timeStamp":1680386285093}],"result":"SUCCESS","precondition":false,"level":2},{"number":45,"description":"Santy enters \u00271004776890\u0027 into Campo numero de cedula para finalizar la compra","duration":644,"startTime":"2023-04-01T17:58:05.095341-04:00[America/Caracas]","screenshots":[{"screenshot":"22ce698dd032345500a96ad510b64aaae226513ed73bc10330cd63e593db6bf4.png","timeStamp":1680386285107},{"screenshot":"27ddcf72657ef3becd155b85430ff1bbbc4fa2bf4896920db650fd46285f6a1d.png","timeStamp":1680386285738}],"result":"SUCCESS","precondition":false,"level":2},{"number":46,"description":"Santy clears field Campo nombre para finalizar la compra","duration":384,"startTime":"2023-04-01T17:58:05.740893800-04:00[America/Caracas]","screenshots":[{"screenshot":"27ddcf72657ef3becd155b85430ff1bbbc4fa2bf4896920db650fd46285f6a1d.png","timeStamp":1680386285753},{"screenshot":"52010c98e4b0158ff0898530e442557ab1079d280a715a7ce61fd0a28e5df333.png","timeStamp":1680386286124}],"result":"SUCCESS","precondition":false,"level":2},{"number":47,"description":"Santy enters \u0027Juan\u0027 into Campo nombre para finalizar la compra","duration":604,"startTime":"2023-04-01T17:58:06.126075900-04:00[America/Caracas]","screenshots":[{"screenshot":"52010c98e4b0158ff0898530e442557ab1079d280a715a7ce61fd0a28e5df333.png","timeStamp":1680386286138},{"screenshot":"3f50f9c1eb7186bf9fe76b02f6229f7c780ef19d2a7f0d34beb1a69aaae0cd7b.png","timeStamp":1680386286730}],"result":"SUCCESS","precondition":false,"level":2},{"number":48,"description":"Santy clears field Campo apellido para finalizar la compra","duration":388,"startTime":"2023-04-01T17:58:06.731340700-04:00[America/Caracas]","screenshots":[{"screenshot":"3f50f9c1eb7186bf9fe76b02f6229f7c780ef19d2a7f0d34beb1a69aaae0cd7b.png","timeStamp":1680386286741},{"screenshot":"833dd6ce37d23d6fba5644e792e96dd126126f68cabd85047b8cdbf85cdc98b4.png","timeStamp":1680386287120}],"result":"SUCCESS","precondition":false,"level":2},{"number":49,"description":"Santy enters \u0027Perez\u0027 into Campo apellido para finalizar la compra","duration":601,"startTime":"2023-04-01T17:58:07.122520300-04:00[America/Caracas]","screenshots":[{"screenshot":"833dd6ce37d23d6fba5644e792e96dd126126f68cabd85047b8cdbf85cdc98b4.png","timeStamp":1680386287131},{"screenshot":"039a0d59d6d553d4f032a21b462bcee74286fb63a7ca0b98b8ca1b07fa2ad5ce.png","timeStamp":1680386287724}],"result":"SUCCESS","precondition":false,"level":2},{"number":50,"description":"Santy clicks on Click en aceptar terminos  para finalizar la compra","duration":415,"startTime":"2023-04-01T17:58:07.725093300-04:00[America/Caracas]","screenshots":[{"screenshot":"039a0d59d6d553d4f032a21b462bcee74286fb63a7ca0b98b8ca1b07fa2ad5ce.png","timeStamp":1680386287738},{"screenshot":"97b2e7169d78fc18a22b98858f6ef1223f9f47a9d3bbbe704379408854e1e92e.png","timeStamp":1680386288140}],"result":"SUCCESS","precondition":false,"level":2},{"number":51,"description":"Santy clicks on Click en autotizo tratamiento de datos  para finalizar la compra","duration":405,"startTime":"2023-04-01T17:58:08.142335500-04:00[America/Caracas]","screenshots":[{"screenshot":"97b2e7169d78fc18a22b98858f6ef1223f9f47a9d3bbbe704379408854e1e92e.png","timeStamp":1680386288151},{"screenshot":"37a782235dc209f19529701286107416e0436c2f5bc4af2e7a063d3a6b5cd387.png","timeStamp":1680386288547}],"result":"SUCCESS","precondition":false,"level":2},{"number":52,"description":"Santy clicks on Boton continuar para finalizar la compra","duration":662,"startTime":"2023-04-01T17:58:08.548818600-04:00[America/Caracas]","screenshots":[{"screenshot":"37a782235dc209f19529701286107416e0436c2f5bc4af2e7a063d3a6b5cd387.png","timeStamp":1680386288559},{"screenshot":"2e5862f3aeea96a9822455880bbcb341d63aac71963cdeb2eb1f45a9e0846ecc.png","timeStamp":1680386289210}],"result":"SUCCESS","precondition":false,"level":2}]},{"number":53,"description":"Santy elegir fecha entrega","duration":6154,"startTime":"2023-04-01T17:58:09.233066800-04:00[America/Caracas]","screenshots":[{"screenshot":"2e5862f3aeea96a9822455880bbcb341d63aac71963cdeb2eb1f45a9e0846ecc.png","timeStamp":1680386289247},{"screenshot":"9c890713b96198a6f4f3688a8a6d7b994eb0b07f7a7a98821305767630d2a8c0.png","timeStamp":1680386295387}],"result":"SUCCESS","precondition":false,"level":1,"children":[{"number":54,"description":"Santy clicks on Campo para selecionar fecha de entrega","duration":715,"startTime":"2023-04-01T17:58:11.161185900-04:00[America/Caracas]","screenshots":[{"screenshot":"4e2205a8b9729a36b2ee33c9fe036c7ae647a3539392187a7596d126853f6fa7.png","timeStamp":1680386291437},{"screenshot":"93074f824c9ebfee121d821f3319608d57638a666ff33a77e4cce3befe731330.png","timeStamp":1680386291876}],"result":"SUCCESS","precondition":false,"level":2},{"number":55,"description":"Santy clicks on Campo para selecionar  el dia de fecha de entrega","duration":545,"startTime":"2023-04-01T17:58:12.243524600-04:00[America/Caracas]","screenshots":[{"screenshot":"0470a2e4e57e9cc49c4a6aef0747c7abfdcb9d9363b7ea07ca44169864549dad.png","timeStamp":1680386292411},{"screenshot":"331cfdffcd7f2e91f0aca12a19707a6ef29119b188bd97f855c9c1df3f81dd0c.png","timeStamp":1680386292789}],"result":"SUCCESS","precondition":false,"level":2},{"number":56,"description":"Santy clicks on Boton  para guardar la  fecha de entrega","duration":1215,"startTime":"2023-04-01T17:58:14.149420400-04:00[America/Caracas]","screenshots":[{"screenshot":"95bd8930d9496476afd85a4af5288189acff5273f11cf966dc2e902db6be5aec.png","timeStamp":1680386294320},{"screenshot":"9c890713b96198a6f4f3688a8a6d7b994eb0b07f7a7a98821305767630d2a8c0.png","timeStamp":1680386295365}],"result":"SUCCESS","precondition":false,"level":2}]}]},{"number":57,"description":"Then Se deberia observar el producto seleccionado en el carrito de compras","duration":245,"startTime":"2023-04-01T17:58:15.402755700-04:00[America/Caracas]","screenshots":[{"screenshot":"2f13c7e13efa8edaab27dd11691693d10a19220f29c342e2274be85a1d8a7c30.png","timeStamp":1680386295647}],"result":"SUCCESS","precondition":false,"level":0}],"userStory":{"id":"comprar-producto-exito","storyName":"Comprar producto exito","path":"file:///C:/Users/pc/Documents/ProyectoScreenPlayExito/src/test/resources/features/comprarproducto.feature","narrative":"  Yo como usuario de la pagina del Exito\n  Quiero poder comprar un producto\n  Para poder tenerlo en mi casa","type":"feature"},"featureTag":{"name":"Features/Comprar producto exito","type":"feature","displayName":"Features/Comprar producto exito"},"title":"Comprar producto exito","tags":[{"name":"ComprarProducto","type":"tag","displayName":"ComprarProducto"},{"name":"Comprar producto exito","type":"feature","displayName":"Comprar producto exito"}],"startTime":"2023-04-01T17:56:34.806409800-04:00[America/Caracas]","duration":100844,"projectKey":"","sessionId":"c40152f9770b08af94fed9da8ce0114d","driver":"chrome","isManualTestingUpToDate":false,"manual":false,"testSource":"Cucumber","actors":[{"name":"Santy","can":["browse the web"]}],"result":"SUCCESS"}